visvis/__init__.py
visvis/freezeHelp.py
visvis/pypoints.py
visvis/backends/__init__.py
visvis/backends/backend_fltk.py
visvis/backends/backend_glfw.py
visvis/backends/backend_gtk.py
visvis/backends/backend_pyqt4.py
visvis/backends/backend_pyqt5.py
visvis/backends/backend_pyside.py
visvis/backends/backend_pyside2.py
visvis/backends/backend_pyside6.py
visvis/backends/backend_wx.py
visvis/backends/qtcommon.py
visvis/core/__init__.py
visvis/core/axes.py
visvis/core/axises.py
visvis/core/base.py
visvis/core/baseFigure.py
visvis/core/baseTexture.py
visvis/core/baseWibjects.py
visvis/core/cameras.py
visvis/core/constants.py
visvis/core/events.py
visvis/core/light.py
visvis/core/line.py
visvis/core/misc.py
visvis/core/orientation.py
visvis/core/shaders.py
visvis/core/shaders_2.py
visvis/core/shaders_3.py
visvis/core/shaders_m.py
visvis/functions/__init__.py
visvis/functions/aVolume.py
visvis/functions/axis.py
visvis/functions/bar.py
visvis/functions/bar3.py
visvis/functions/boxplot.py
visvis/functions/callLater.py
visvis/functions/cla.py
visvis/functions/clf.py
visvis/functions/close.py
visvis/functions/closeAll.py
visvis/functions/colorbar.py
visvis/functions/draw.py
visvis/functions/figure.py
visvis/functions/gca.py
visvis/functions/gcf.py
visvis/functions/getOpenGlInfo.py
visvis/functions/getframe.py
visvis/functions/ginput.py
visvis/functions/grid.py
visvis/functions/help.py
visvis/functions/hist.py
visvis/functions/imread.py
visvis/functions/imshow.py
visvis/functions/imwrite.py
visvis/functions/isocontour.py
visvis/functions/isosurface.py
visvis/functions/kde.py
visvis/functions/legend.py
visvis/functions/mesh.py
visvis/functions/meshRead.py
visvis/functions/meshWrite.py
visvis/functions/movieRead.py
visvis/functions/movieShow.py
visvis/functions/movieWrite.py
visvis/functions/peaks.py
visvis/functions/plot.py
visvis/functions/polarplot.py
visvis/functions/processEvents.py
visvis/functions/record.py
visvis/functions/reportIssue.py
visvis/functions/screenshot.py
visvis-1.15.0.dist-info/LICENSE
visvis-1.15.0.dist-info/WHEEL
visvis-1.15.0.dist-info/METADATA
visvis-1.15.0.dist-info/RECORD
