Metadata-Version: 2.1
Name: visvis
Version: 1.15.0
Summary: The object oriented approach to visualization 
Keywords: visualization,opengl,2d,3d,medical imaging
Author: Almar Klein
Requires-Python: >= 2.7
Classifier: Development Status :: 4 - Beta
Classifier: Intended Audience :: Science/Research
Classifier: Intended Audience :: Education
Classifier: Intended Audience :: Developers
Classifier: Topic :: Scientific/Engineering :: Visualization
Classifier: License :: OSI Approved :: BSD License
Classifier: Operating System :: MacOS :: MacOS X
Classifier: Operating System :: Microsoft :: Windows
Classifier: Operating System :: POSIX
Classifier: Programming Language :: Python
Classifier: Programming Language :: Python :: 2.7
Classifier: Programming Language :: Python :: 3.4
Classifier: Programming Language :: Python :: 3.5
Classifier: Programming Language :: Python :: 3.6
Classifier: Programming Language :: Python :: 3.7
Classifier: Programming Language :: Python :: 3.8
Classifier: Programming Language :: Python :: 3.9
Classifier: Programming Language :: Python :: 3.10
Classifier: Programming Language :: Python :: 3.11
Classifier: Programming Language :: Python :: 3.12
Classifier: Programming Language :: Python :: 3.13
Requires-Dist: numpy
Requires-Dist: pyOpenGl
Project-URL: Documentation, https://github.com/almarklein/visvis/wiki
Project-URL: Homepage, https://github.com/almarklein/visvis
Project-URL: Repository, https://github.com/almarklein/visvis
